diff_edit/__init__.py
diff_edit/model/__init__.py
diff_edit/model/constants.py
diff_edit/model/diff_edit_model.py
diff_edit/model/image_processing.py
diff_edit/model/mask_generation.py
diff_edit/model/mask_inpainting.py
diff_edit/model/model_composer.py
diff_edit/scripts/image_edit.py
diff_edit/scripts/mask.png
diff_edit/scripts/result.png
diffedit-0.0.2rc10.dist-info/LICENSE
diffedit-0.0.2rc10.dist-info/METADATA
diffedit-0.0.2rc10.dist-info/WHEEL
diffedit-0.0.2rc10.dist-info/entry_points.txt
diffedit-0.0.2rc10.dist-info/RECORD
