Metadata-Version: 2.1
Name: DiffEdit
Version: 0.0.2rc10
Summary: An implementation of the DiffEdit algorithm for prompt-based mask creation and inpating. For more information, see the Readme file.
License: Apache-2.0
Author: Gennaro Farina
Requires-Python: >=3.10,<4.0
Classifier: License :: OSI Approved :: Apache Software License
Classifier: Programming Language :: Python :: 3
Classifier: Programming Language :: Python :: 3.10
Classifier: Programming Language :: Python :: 3.11
Classifier: Programming Language :: Python :: 3.12
Provides-Extra: dev
Provides-Extra: test
Requires-Dist: accelerate (==0.26.1)
Requires-Dist: black[jupyter] (==23.3.0) ; extra == "dev"
Requires-Dist: diffusers (>=0.25)
Requires-Dist: docformatter (==1.5.1) ; extra == "dev"
Requires-Dist: docstr-coverage (==2.2.0) ; extra == "dev"
Requires-Dist: fastai (==2.7.13)
Requires-Dist: numpy (==1.26.2)
Requires-Dist: opencv_python (>=4.9,<5.0)
Requires-Dist: pre-commit (==3.3.1) ; extra == "dev"
Requires-Dist: pytest (==7.3.1) ; extra == "test"
Requires-Dist: pytest-cov (==4.0.0) ; extra == "test"
Requires-Dist: pytest-sugar (==0.9.7) ; extra == "test"
Requires-Dist: pytest-xdist (==3.2.1) ; extra == "test"
Requires-Dist: requests (==2.27.1)
Requires-Dist: ruff (==0.0.264) ; extra == "dev"
Requires-Dist: setuptools (>=69.1.1,<70.0.0)
Requires-Dist: torch (>=2.0.0,!=2.0.1,!=2.1.0)
Requires-Dist: tqdm
Requires-Dist: transformers (==4.36.2)
Requires-Dist: twine (>=4.0.0,<5) ; extra == "dev"
